Metadata-Version: 1.2
Name: rymysql
Version: 0.2.0
Summary: mysql.connector wrapper
Home-page: UNKNOWN
Author: Ryan Rickgauer
Author-email: rrickgauer1@gmail.com
License: UNKNOWN
Project-URL: Documentation, https://github.com/rrickgauer/rymysql
Project-URL: Source Code, https://github.com/rrickgauer/rymysql
Project-URL: Issue Tracker, https://github.com/rrickgauer/rymysql/issues
Platform: UNKNOWN
